farseer-0.1.0.dist-info/METADATA
farseer-0.1.0.dist-info/WHEEL
farseer-0.1.0.dist-info/licenses/LICENSE
farseer/__init__.py
farseer/_farseer.cpython-313-x86_64-linux-gnu.so
farseer/utilities.py
stan/README.md
stan/cmdstan_version.txt
stan/prophet
stan/prophet.stan
stan/prophet_model
farseer-0.1.0.dist-info/RECORD
