Metadata-Version: 2.4
Name: farseer
Version: 0.1.0
Classifier: Programming Language :: Rust
Classifier: Programming Language :: Python :: Implementation :: CPython
Classifier: Programming Language :: Python :: Implementation :: PyPy
Classifier: Programming Language :: Python :: 3
Classifier: Programming Language :: Python :: 3.11
Classifier: Programming Language :: Python :: 3.12
Classifier: Programming Language :: Python :: 3.13
Classifier: Development Status :: 4 - Beta
Classifier: Intended Audience :: Science/Research
Classifier: Intended Audience :: Developers
Classifier: Topic :: Scientific/Engineering
Classifier: Topic :: Scientific/Engineering :: Information Analysis
Classifier: License :: OSI Approved :: GNU General Public License v3 or later (GPLv3+)
Classifier: Operating System :: POSIX :: Linux
Classifier: Operating System :: MacOS
Requires-Dist: cmdstanpy>=1.0.4
Requires-Dist: numpy>=1.15.4
Requires-Dist: matplotlib>=2.0.0
Requires-Dist: pandas>=1.0.4
Requires-Dist: polars>=0.20.0
Requires-Dist: pyarrow>=10.0
Requires-Dist: tqdm>=4.36.1
Requires-Dist: pytest>=7.0 ; extra == 'dev'
Requires-Dist: pytest-cov>=4.0 ; extra == 'dev'
Requires-Dist: tqdm>=4.36.1 ; extra == 'parallel'
Requires-Dist: jupyter>=1.0 ; extra == 'notebook'
Requires-Dist: notebook>=7.0 ; extra == 'notebook'
Requires-Dist: ipykernel>=6.0 ; extra == 'notebook'
Requires-Dist: prophet>=1.1 ; extra == 'notebook'
Requires-Dist: pandas>=1.0 ; extra == 'notebook'
Requires-Dist: seaborn>=0.12 ; extra == 'notebook'
Requires-Dist: scikit-learn>=1.0 ; extra == 'notebook'
Provides-Extra: dev
Provides-Extra: parallel
Provides-Extra: notebook
License-File: LICENSE
Summary: Fast Bayesian time series forecasting in Rust, with Python bindings
Keywords: forecasting,time-series,prophet,bayesian,rust
Home-Page: https://github.com/ryanbieber/seer
Author-email: Ryan Bieber <ryan.bieber@protonmail.com>
License: GPL-3.0-or-later
Requires-Python: >=3.11
Project-URL: Homepage, https://github.com/ryanbieber/seer
Project-URL: Documentation, https://github.com/ryanbieber/seer
Project-URL: Repository, https://github.com/ryanbieber/seer
Project-URL: Issues, https://github.com/ryanbieber/seer/issues
